{
  "state": "ND",
  "state_name": "North Dakota",
  "year": 2024,
  "total": 42,
  "scraped_at": "2026-01-30T23:09:02.992190+00:00",
  "unopposed_candidates": [
    {
      "state": "ND",
      "office": "US Senate",
      "district": "Statewide",
      "candidate": "Katrina Christiansen",
      "party": "Democrat",
      "unopposed_in": "Primary",
      "source": "Ballotpedia"
    },
    {
      "state": "ND",
      "office": "US Senate",
      "district": "Statewide",
      "candidate": "Kevin Cramer",
      "party": "Republican",
      "unopposed_in": "Primary",
      "source": "Ballotpedia"
    },
    {
      "state": "ND",
      "office": "State Senate",
      "district": "District 4",
      "candidate": "Chuck Walen",
      "party": "Republican",
      "unopposed_in": "Primary & General",
      "source": "Ballotpedia"
    },
    {
      "state": "ND",
      "office": "State Senate",
      "district": "District 8",
      "candidate": "Jeffery Magrum",
      "party": "Republican",
      "unopposed_in": "General",
      "source": "Ballotpedia"
    },
    {
      "state": "ND",
      "office": "State Senate",
      "district": "District 22",
      "candidate": "Mark Weber",
      "party": "Republican",
      "unopposed_in": "Primary & General",
      "source": "Ballotpedia"
    },
    {
      "state": "ND",
      "office": "State Senate",
      "district": "District 26",
      "candidate": "Dale Patten",
      "party": "Republican",
      "unopposed_in": "Primary & General",
      "source": "Ballotpedia"
    },
    {
      "state": "ND",
      "office": "State Senate",
      "district": "District 32",
      "candidate": "Dick Dever",
      "party": "Republican",
      "unopposed_in": "Primary & General",
      "source": "Ballotpedia"
    },
    {
      "state": "ND",
      "office": "State Senate",
      "district": "District 36",
      "candidate": "Desiree Van Oosting",
      "party": "Republican",
      "unopposed_in": "Primary & General",
      "source": "Ballotpedia"
    },
    {
      "state": "ND",
      "office": "State Senate",
      "district": "District 38",
      "candidate": "David Hogue",
      "party": "Republican",
      "unopposed_in": "Primary & General",
      "source": "Ballotpedia"
    },
    {
      "state": "ND",
      "office": "State Senate",
      "district": "District 40",
      "candidate": "Jose Castaneda",
      "party": "Republican",
      "unopposed_in": "Primary & General",
      "source": "Ballotpedia"
    },
    {
      "state": "ND",
      "office": "State Senate",
      "district": "District 44",
      "candidate": "Joshua A. Boschee",
      "party": "Democrat",
      "unopposed_in": "Primary & General",
      "source": "Ballotpedia"
    },
    {
      "state": "ND",
      "office": "State Senate",
      "district": "District 2",
      "candidate": "Rosemary Tanberg",
      "party": "Democrat",
      "unopposed_in": "Primary",
      "source": "Ballotpedia"
    },
    {
      "state": "ND",
      "office": "State Senate",
      "district": "District 10",
      "candidate": "Ryan Braunberger",
      "party": "Democrat",
      "unopposed_in": "Primary",
      "source": "Ballotpedia"
    },
    {
      "state": "ND",
      "office": "State Senate",
      "district": "District 10",
      "candidate": "George Roughead",
      "party": "Republican",
      "unopposed_in": "Primary",
      "source": "Ballotpedia"
    },
    {
      "state": "ND",
      "office": "State Senate",
      "district": "District 12",
      "candidate": "Olivia Schloegel",
      "party": "Democrat",
      "unopposed_in": "Primary",
      "source": "Ballotpedia"
    },
    {
      "state": "ND",
      "office": "State Senate",
      "district": "District 12",
      "candidate": "Cole Conley",
      "party": "Republican",
      "unopposed_in": "Primary",
      "source": "Ballotpedia"
    },
    {
      "state": "ND",
      "office": "State Senate",
      "district": "District 14",
      "candidate": "Mark Nelson",
      "party": "Democrat",
      "unopposed_in": "Primary",
      "source": "Ballotpedia"
    },
    {
      "state": "ND",
      "office": "State Senate",
      "district": "District 16",
      "candidate": "Heather Tyulyandin",
      "party": "Democrat",
      "unopposed_in": "Primary",
      "source": "Ballotpedia"
    },
    {
      "state": "ND",
      "office": "State Senate",
      "district": "District 16",
      "candidate": "David Clemens",
      "party": "Republican",
      "unopposed_in": "Primary",
      "source": "Ballotpedia"
    },
    {
      "state": "ND",
      "office": "State Senate",
      "district": "District 18",
      "candidate": "Kyle Thorson",
      "party": "Democrat",
      "unopposed_in": "Primary",
      "source": "Ballotpedia"
    },
    {
      "state": "ND",
      "office": "State Senate",
      "district": "District 18",
      "candidate": "Scott Meyer",
      "party": "Republican",
      "unopposed_in": "Primary",
      "source": "Ballotpedia"
    },
    {
      "state": "ND",
      "office": "State Senate",
      "district": "District 20",
      "candidate": "John Pederson",
      "party": "Democrat",
      "unopposed_in": "Primary",
      "source": "Ballotpedia"
    },
    {
      "state": "ND",
      "office": "State Senate",
      "district": "District 20",
      "candidate": "Randy Lemm",
      "party": "Republican",
      "unopposed_in": "Primary",
      "source": "Ballotpedia"
    },
    {
      "state": "ND",
      "office": "State Senate",
      "district": "District 24",
      "candidate": "Knut Gjovik",
      "party": "Democrat",
      "unopposed_in": "Primary",
      "source": "Ballotpedia"
    },
    {
      "state": "ND",
      "office": "State Senate",
      "district": "District 24",
      "candidate": "Mike Wobbema",
      "party": "Republican",
      "unopposed_in": "Primary",
      "source": "Ballotpedia"
    },
    {
      "state": "ND",
      "office": "State Senate",
      "district": "District 28",
      "candidate": "Richard Schlosser",
      "party": "Democrat",
      "unopposed_in": "Primary",
      "source": "Ballotpedia"
    },
    {
      "state": "ND",
      "office": "State Senate",
      "district": "District 28",
      "candidate": "Robert Erbele",
      "party": "Republican",
      "unopposed_in": "Primary",
      "source": "Ballotpedia"
    },
    {
      "state": "ND",
      "office": "State Senate",
      "district": "District 30",
      "candidate": "Matthew Zimny",
      "party": "Democrat",
      "unopposed_in": "Primary",
      "source": "Ballotpedia"
    },
    {
      "state": "ND",
      "office": "State Senate",
      "district": "District 34",
      "candidate": "Joshua Johnson",
      "party": "Democrat",
      "unopposed_in": "Primary",
      "source": "Ballotpedia"
    },
    {
      "state": "ND",
      "office": "State Senate",
      "district": "District 34",
      "candidate": "Justin Gerhardt",
      "party": "Republican",
      "unopposed_in": "Primary",
      "source": "Ballotpedia"
    },
    {
      "state": "ND",
      "office": "State Senate",
      "district": "District 42",
      "candidate": "Rodney Gigstad",
      "party": "Democrat",
      "unopposed_in": "Primary",
      "source": "Ballotpedia"
    },
    {
      "state": "ND",
      "office": "State Senate",
      "district": "District 44",
      "candidate": "Andrew Nyhus",
      "party": "Republican",
      "unopposed_in": "Primary",
      "source": "Ballotpedia"
    },
    {
      "state": "ND",
      "office": "State Senate",
      "district": "District 46",
      "candidate": "Jessica Arneson",
      "party": "Democrat",
      "unopposed_in": "Primary",
      "source": "Ballotpedia"
    },
    {
      "state": "ND",
      "office": "State Senate",
      "district": "District 46",
      "candidate": "Michelle Powers",
      "party": "Republican",
      "unopposed_in": "Primary",
      "source": "Ballotpedia"
    },
    {
      "state": "ND",
      "office": "State House",
      "district": "District 4",
      "candidate": "Clayton Fegley",
      "party": "Republican",
      "unopposed_in": "Primary & General",
      "source": "Ballotpedia"
    },
    {
      "state": "ND",
      "office": "State House",
      "district": "District 4",
      "candidate": "Lisa Finley-DeVille",
      "party": "Democrat",
      "unopposed_in": "Primary",
      "source": "Ballotpedia"
    },
    {
      "state": "ND",
      "office": "State House",
      "district": "District 4",
      "candidate": "Ronald Brugh",
      "party": "Republican",
      "unopposed_in": "Primary",
      "source": "Ballotpedia"
    },
    {
      "state": "ND",
      "office": "State House",
      "district": "District 10",
      "candidate": "Hamida Dakane",
      "party": "Democrat",
      "unopposed_in": "Primary",
      "source": "Ballotpedia"
    },
    {
      "state": "ND",
      "office": "State House",
      "district": "District 22",
      "candidate": "Darrell Hansen",
      "party": "Democrat",
      "unopposed_in": "Primary",
      "source": "Ballotpedia"
    },
    {
      "state": "ND",
      "office": "State House",
      "district": "District 32",
      "candidate": "Shari Orser",
      "party": "Democrat",
      "unopposed_in": "Primary",
      "source": "Ballotpedia"
    },
    {
      "state": "ND",
      "office": "State House",
      "district": "District 38",
      "candidate": "Lisa Hermosillo",
      "party": "Democrat",
      "unopposed_in": "Primary",
      "source": "Ballotpedia"
    },
    {
      "state": "ND",
      "office": "State House",
      "district": "District 40",
      "candidate": "Alexandra Deufel",
      "party": "Democrat",
      "unopposed_in": "Primary",
      "source": "Ballotpedia"
    }
  ]
}
