{
  "state": "WV",
  "state_name": "West Virginia",
  "year": 2024,
  "total": 150,
  "scraped_at": "2026-01-30T23:15:27.990596+00:00",
  "unopposed_candidates": [
    {
      "state": "WV",
      "office": "US House",
      "district": "District 2",
      "candidate": "Steven Wendelin",
      "party": "Democrat",
      "unopposed_in": "Primary",
      "source": "Ballotpedia"
    },
    {
      "state": "WV",
      "office": "Governor",
      "district": "Statewide",
      "candidate": "Steve Williams",
      "party": "Democrat",
      "unopposed_in": "Primary",
      "source": "Ballotpedia"
    },
    {
      "state": "WV",
      "office": "Governor",
      "district": "Statewide",
      "candidate": "Chase Linko-Looper",
      "party": "Unknown",
      "unopposed_in": "Primary",
      "source": "Ballotpedia"
    },
    {
      "state": "WV",
      "office": "State Senate",
      "district": "District 1",
      "candidate": "Ryan Weld",
      "party": "Republican",
      "unopposed_in": "General",
      "source": "Ballotpedia"
    },
    {
      "state": "WV",
      "office": "State Senate",
      "district": "District 2",
      "candidate": "Christopher Rose",
      "party": "Republican",
      "unopposed_in": "General",
      "source": "Ballotpedia"
    },
    {
      "state": "WV",
      "office": "State Senate",
      "district": "District 3",
      "candidate": "Donna Boley",
      "party": "Republican",
      "unopposed_in": "Primary & General",
      "source": "Ballotpedia"
    },
    {
      "state": "WV",
      "office": "State Senate",
      "district": "District 7",
      "candidate": "Rupie Phillips",
      "party": "Republican",
      "unopposed_in": "Primary & General",
      "source": "Ballotpedia"
    },
    {
      "state": "WV",
      "office": "State Senate",
      "district": "District 8",
      "candidate": "Glenn Jeffries",
      "party": "Republican",
      "unopposed_in": "Primary & General",
      "source": "Ballotpedia"
    },
    {
      "state": "WV",
      "office": "State Senate",
      "district": "District 12",
      "candidate": "Patrick Martin",
      "party": "Republican",
      "unopposed_in": "Primary & General",
      "source": "Ballotpedia"
    },
    {
      "state": "WV",
      "office": "State Senate",
      "district": "District 4",
      "candidate": "Dwayne Russell",
      "party": "Democrat",
      "unopposed_in": "Primary",
      "source": "Ballotpedia"
    },
    {
      "state": "WV",
      "office": "State Senate",
      "district": "District 4",
      "candidate": "Amy Nichole Grady",
      "party": "Republican",
      "unopposed_in": "Primary",
      "source": "Ballotpedia"
    },
    {
      "state": "WV",
      "office": "State Senate",
      "district": "District 5",
      "candidate": "Ric Griffith",
      "party": "Democrat",
      "unopposed_in": "Primary",
      "source": "Ballotpedia"
    },
    {
      "state": "WV",
      "office": "State Senate",
      "district": "District 6",
      "candidate": "Randall Fowler",
      "party": "Democrat",
      "unopposed_in": "Primary",
      "source": "Ballotpedia"
    },
    {
      "state": "WV",
      "office": "State Senate",
      "district": "District 9",
      "candidate": "Christy Cardwell",
      "party": "Democrat",
      "unopposed_in": "Primary",
      "source": "Ballotpedia"
    },
    {
      "state": "WV",
      "office": "State Senate",
      "district": "District 10",
      "candidate": "Jack Woodrum",
      "party": "Republican",
      "unopposed_in": "Primary",
      "source": "Ballotpedia"
    },
    {
      "state": "WV",
      "office": "State Senate",
      "district": "District 11",
      "candidate": "Mandy Smith Weirich",
      "party": "Democrat",
      "unopposed_in": "Primary",
      "source": "Ballotpedia"
    },
    {
      "state": "WV",
      "office": "State Senate",
      "district": "District 13",
      "candidate": "Joey Garcia",
      "party": "Democrat",
      "unopposed_in": "Primary",
      "source": "Ballotpedia"
    },
    {
      "state": "WV",
      "office": "State Senate",
      "district": "District 13",
      "candidate": "Jonathan Board",
      "party": "Republican",
      "unopposed_in": "Primary",
      "source": "Ballotpedia"
    },
    {
      "state": "WV",
      "office": "State Senate",
      "district": "District 14",
      "candidate": "Randy E. Smith",
      "party": "Republican",
      "unopposed_in": "Primary",
      "source": "Ballotpedia"
    },
    {
      "state": "WV",
      "office": "State Senate",
      "district": "District 14",
      "candidate": "Betsy Orndoff-Sayers",
      "party": "Other",
      "unopposed_in": "Primary",
      "source": "Ballotpedia"
    },
    {
      "state": "WV",
      "office": "State Senate",
      "district": "District 15",
      "candidate": "Anthony Murray",
      "party": "Democrat",
      "unopposed_in": "Primary",
      "source": "Ballotpedia"
    },
    {
      "state": "WV",
      "office": "State Senate",
      "district": "District 16",
      "candidate": "John Doyle",
      "party": "Democrat",
      "unopposed_in": "Primary",
      "source": "Ballotpedia"
    },
    {
      "state": "WV",
      "office": "State Senate",
      "district": "District 17",
      "candidate": "Bil Lepp",
      "party": "Democrat",
      "unopposed_in": "Primary",
      "source": "Ballotpedia"
    },
    {
      "state": "WV",
      "office": "State House",
      "district": "District 1",
      "candidate": "Pat McGeehan",
      "party": "Republican",
      "unopposed_in": "Primary & General",
      "source": "Ballotpedia"
    },
    {
      "state": "WV",
      "office": "State House",
      "district": "District 8",
      "candidate": "David Kelly",
      "party": "Republican",
      "unopposed_in": "General",
      "source": "Ballotpedia"
    },
    {
      "state": "WV",
      "office": "State House",
      "district": "District 9",
      "candidate": "Trenton Barnhart",
      "party": "Republican",
      "unopposed_in": "Primary & General",
      "source": "Ballotpedia"
    },
    {
      "state": "WV",
      "office": "State House",
      "district": "District 10",
      "candidate": "Everette Anderson",
      "party": "Republican",
      "unopposed_in": "Primary & General",
      "source": "Ballotpedia"
    },
    {
      "state": "WV",
      "office": "State House",
      "district": "District 11",
      "candidate": "Bob Fehrenbacher",
      "party": "Republican",
      "unopposed_in": "Primary & General",
      "source": "Ballotpedia"
    },
    {
      "state": "WV",
      "office": "State House",
      "district": "District 12",
      "candidate": "Vernon Criss",
      "party": "Republican",
      "unopposed_in": "Primary & General",
      "source": "Ballotpedia"
    },
    {
      "state": "WV",
      "office": "State House",
      "district": "District 13",
      "candidate": "Scot Heckert",
      "party": "Republican",
      "unopposed_in": "Primary & General",
      "source": "Ballotpedia"
    },
    {
      "state": "WV",
      "office": "State House",
      "district": "District 16",
      "candidate": "Joe Parsons",
      "party": "Republican",
      "unopposed_in": "General",
      "source": "Ballotpedia"
    },
    {
      "state": "WV",
      "office": "State House",
      "district": "District 17",
      "candidate": "Jonathan Pinson",
      "party": "Republican",
      "unopposed_in": "General",
      "source": "Ballotpedia"
    },
    {
      "state": "WV",
      "office": "State House",
      "district": "District 19",
      "candidate": "Kathie Hess Crouse",
      "party": "Republican",
      "unopposed_in": "General",
      "source": "Ballotpedia"
    },
    {
      "state": "WV",
      "office": "State House",
      "district": "District 22",
      "candidate": "Daniel Linville",
      "party": "Republican",
      "unopposed_in": "General",
      "source": "Ballotpedia"
    },
    {
      "state": "WV",
      "office": "State House",
      "district": "District 26",
      "candidate": "Matthew Rohrbach",
      "party": "Republican",
      "unopposed_in": "Primary & General",
      "source": "Ballotpedia"
    },
    {
      "state": "WV",
      "office": "State House",
      "district": "District 31",
      "candidate": "Margitta Mazzocchi",
      "party": "Republican",
      "unopposed_in": "Primary & General",
      "source": "Ballotpedia"
    },
    {
      "state": "WV",
      "office": "State House",
      "district": "District 34",
      "candidate": "Mark Dean",
      "party": "Republican",
      "unopposed_in": "General",
      "source": "Ballotpedia"
    },
    {
      "state": "WV",
      "office": "State House",
      "district": "District 35",
      "candidate": "Adam Vance",
      "party": "Republican",
      "unopposed_in": "Primary & General",
      "source": "Ballotpedia"
    },
    {
      "state": "WV",
      "office": "State House",
      "district": "District 43",
      "candidate": "Christopher Toney",
      "party": "Republican",
      "unopposed_in": "Primary & General",
      "source": "Ballotpedia"
    },
    {
      "state": "WV",
      "office": "State House",
      "district": "District 45",
      "candidate": "Eric Brooks",
      "party": "Republican",
      "unopposed_in": "Primary & General",
      "source": "Ballotpedia"
    },
    {
      "state": "WV",
      "office": "State House",
      "district": "District 58",
      "candidate": "Walter Hall",
      "party": "Republican",
      "unopposed_in": "Primary & General",
      "source": "Ballotpedia"
    },
    {
      "state": "WV",
      "office": "State House",
      "district": "District 59",
      "candidate": "Andy Shamblin",
      "party": "Republican",
      "unopposed_in": "Primary & General",
      "source": "Ballotpedia"
    },
    {
      "state": "WV",
      "office": "State House",
      "district": "District 60",
      "candidate": "Dana Ferrell",
      "party": "Republican",
      "unopposed_in": "Primary & General",
      "source": "Ballotpedia"
    },
    {
      "state": "WV",
      "office": "State House",
      "district": "District 61",
      "candidate": "Dean Jeffries",
      "party": "Republican",
      "unopposed_in": "Primary & General",
      "source": "Ballotpedia"
    },
    {
      "state": "WV",
      "office": "State House",
      "district": "District 62",
      "candidate": "Roger Hanshaw",
      "party": "Republican",
      "unopposed_in": "General",
      "source": "Ballotpedia"
    },
    {
      "state": "WV",
      "office": "State House",
      "district": "District 63",
      "candidate": "Lori Cowger Dittman",
      "party": "Republican",
      "unopposed_in": "Primary & General",
      "source": "Ballotpedia"
    },
    {
      "state": "WV",
      "office": "State House",
      "district": "District 64",
      "candidate": "Adam Burkhammer",
      "party": "Republican",
      "unopposed_in": "Primary & General",
      "source": "Ballotpedia"
    },
    {
      "state": "WV",
      "office": "State House",
      "district": "District 68",
      "candidate": "Chris Phillips",
      "party": "Republican",
      "unopposed_in": "General",
      "source": "Ballotpedia"
    },
    {
      "state": "WV",
      "office": "State House",
      "district": "District 69",
      "candidate": "Keith Marple",
      "party": "Republican",
      "unopposed_in": "General",
      "source": "Ballotpedia"
    },
    {
      "state": "WV",
      "office": "State House",
      "district": "District 71",
      "candidate": "Laura Kimble",
      "party": "Republican",
      "unopposed_in": "Primary & General",
      "source": "Ballotpedia"
    },
    {
      "state": "WV",
      "office": "State House",
      "district": "District 72",
      "candidate": "Clay Riley",
      "party": "Republican",
      "unopposed_in": "Primary & General",
      "source": "Ballotpedia"
    },
    {
      "state": "WV",
      "office": "State House",
      "district": "District 73",
      "candidate": "Bryan Smith",
      "party": "Republican",
      "unopposed_in": "General",
      "source": "Ballotpedia"
    },
    {
      "state": "WV",
      "office": "State House",
      "district": "District 77",
      "candidate": "Joe Statler",
      "party": "Republican",
      "unopposed_in": "Primary & General",
      "source": "Ballotpedia"
    },
    {
      "state": "WV",
      "office": "State House",
      "district": "District 79",
      "candidate": "Evan Hansen",
      "party": "Democrat",
      "unopposed_in": "Primary & General",
      "source": "Ballotpedia"
    },
    {
      "state": "WV",
      "office": "State House",
      "district": "District 81",
      "candidate": "Anitra Hamilton",
      "party": "Democrat",
      "unopposed_in": "Primary & General",
      "source": "Ballotpedia"
    },
    {
      "state": "WV",
      "office": "State House",
      "district": "District 83",
      "candidate": "George Street",
      "party": "Republican",
      "unopposed_in": "Primary & General",
      "source": "Ballotpedia"
    },
    {
      "state": "WV",
      "office": "State House",
      "district": "District 84",
      "candidate": "D.R. Jennings",
      "party": "Republican",
      "unopposed_in": "General",
      "source": "Ballotpedia"
    },
    {
      "state": "WV",
      "office": "State House",
      "district": "District 85",
      "candidate": "John Paul Hott II",
      "party": "Republican",
      "unopposed_in": "General",
      "source": "Ballotpedia"
    },
    {
      "state": "WV",
      "office": "State House",
      "district": "District 86",
      "candidate": "Bryan Ward",
      "party": "Republican",
      "unopposed_in": "Primary & General",
      "source": "Ballotpedia"
    },
    {
      "state": "WV",
      "office": "State House",
      "district": "District 87",
      "candidate": "Gary G. Howell",
      "party": "Republican",
      "unopposed_in": "Primary & General",
      "source": "Ballotpedia"
    },
    {
      "state": "WV",
      "office": "State House",
      "district": "District 90",
      "candidate": "George Miller",
      "party": "Republican",
      "unopposed_in": "General",
      "source": "Ballotpedia"
    },
    {
      "state": "WV",
      "office": "State House",
      "district": "District 92",
      "candidate": "Michael Hite",
      "party": "Republican",
      "unopposed_in": "Primary & General",
      "source": "Ballotpedia"
    },
    {
      "state": "WV",
      "office": "State House",
      "district": "District 93",
      "candidate": "Michael Hornby",
      "party": "Republican",
      "unopposed_in": "Primary & General",
      "source": "Ballotpedia"
    },
    {
      "state": "WV",
      "office": "State House",
      "district": "District 94",
      "candidate": "Larry D. Kump",
      "party": "Republican",
      "unopposed_in": "Primary & General",
      "source": "Ballotpedia"
    },
    {
      "state": "WV",
      "office": "State House",
      "district": "District 2",
      "candidate": "Olivia Dowler",
      "party": "Democrat",
      "unopposed_in": "Primary",
      "source": "Ballotpedia"
    },
    {
      "state": "WV",
      "office": "State House",
      "district": "District 3",
      "candidate": "David Cantrell",
      "party": "Democrat",
      "unopposed_in": "Primary",
      "source": "Ballotpedia"
    },
    {
      "state": "WV",
      "office": "State House",
      "district": "District 3",
      "candidate": "Jimmy Willis",
      "party": "Republican",
      "unopposed_in": "Primary",
      "source": "Ballotpedia"
    },
    {
      "state": "WV",
      "office": "State House",
      "district": "District 4",
      "candidate": "Jonathan Haught",
      "party": "Democrat",
      "unopposed_in": "Primary",
      "source": "Ballotpedia"
    },
    {
      "state": "WV",
      "office": "State House",
      "district": "District 5",
      "candidate": "Shawn Fluharty",
      "party": "Democrat",
      "unopposed_in": "Primary",
      "source": "Ballotpedia"
    },
    {
      "state": "WV",
      "office": "State House",
      "district": "District 5",
      "candidate": "Thomas Salkovick",
      "party": "Republican",
      "unopposed_in": "Primary",
      "source": "Ballotpedia"
    },
    {
      "state": "WV",
      "office": "State House",
      "district": "District 7",
      "candidate": "Devon Tennant",
      "party": "Democrat",
      "unopposed_in": "Primary",
      "source": "Ballotpedia"
    },
    {
      "state": "WV",
      "office": "State House",
      "district": "District 7",
      "candidate": "Charles Sheedy",
      "party": "Republican",
      "unopposed_in": "Primary",
      "source": "Ballotpedia"
    },
    {
      "state": "WV",
      "office": "State House",
      "district": "District 14",
      "candidate": "Jim Marion",
      "party": "Democrat",
      "unopposed_in": "Primary",
      "source": "Ballotpedia"
    },
    {
      "state": "WV",
      "office": "State House",
      "district": "District 14",
      "candidate": "Dave Foggin",
      "party": "Republican",
      "unopposed_in": "Primary",
      "source": "Ballotpedia"
    },
    {
      "state": "WV",
      "office": "State House",
      "district": "District 15",
      "candidate": "JuliAnna Penfold",
      "party": "Democrat",
      "unopposed_in": "Primary",
      "source": "Ballotpedia"
    },
    {
      "state": "WV",
      "office": "State House",
      "district": "District 18",
      "candidate": "Andrea Meadows",
      "party": "Democrat",
      "unopposed_in": "Primary",
      "source": "Ballotpedia"
    },
    {
      "state": "WV",
      "office": "State House",
      "district": "District 18",
      "candidate": "Jim Butler",
      "party": "Republican",
      "unopposed_in": "Primary",
      "source": "Ballotpedia"
    },
    {
      "state": "WV",
      "office": "State House",
      "district": "District 20",
      "candidate": "Steve Patrick",
      "party": "Democrat",
      "unopposed_in": "Primary",
      "source": "Ballotpedia"
    },
    {
      "state": "WV",
      "office": "State House",
      "district": "District 21",
      "candidate": "Michael Mosteller II",
      "party": "Democrat",
      "unopposed_in": "Primary",
      "source": "Ballotpedia"
    },
    {
      "state": "WV",
      "office": "State House",
      "district": "District 21",
      "candidate": "Jarred Cannon",
      "party": "Republican",
      "unopposed_in": "Primary",
      "source": "Ballotpedia"
    },
    {
      "state": "WV",
      "office": "State House",
      "district": "District 23",
      "candidate": "Amanda Beach-Burge",
      "party": "Democrat",
      "unopposed_in": "Primary",
      "source": "Ballotpedia"
    },
    {
      "state": "WV",
      "office": "State House",
      "district": "District 23",
      "candidate": "Evan Worrell",
      "party": "Republican",
      "unopposed_in": "Primary",
      "source": "Ballotpedia"
    },
    {
      "state": "WV",
      "office": "State House",
      "district": "District 24",
      "candidate": "Billy Wray",
      "party": "Democrat",
      "unopposed_in": "Primary",
      "source": "Ballotpedia"
    },
    {
      "state": "WV",
      "office": "State House",
      "district": "District 24",
      "candidate": "Patrick Lucas",
      "party": "Republican",
      "unopposed_in": "Primary",
      "source": "Ballotpedia"
    },
    {
      "state": "WV",
      "office": "State House",
      "district": "District 25",
      "candidate": "Sean Hornbuckle",
      "party": "Democrat",
      "unopposed_in": "Primary",
      "source": "Ballotpedia"
    },
    {
      "state": "WV",
      "office": "State House",
      "district": "District 25",
      "candidate": "Connie Beaty",
      "party": "Republican",
      "unopposed_in": "Primary",
      "source": "Ballotpedia"
    },
    {
      "state": "WV",
      "office": "State House",
      "district": "District 27",
      "candidate": "Gina Milum",
      "party": "Democrat",
      "unopposed_in": "Primary",
      "source": "Ballotpedia"
    },
    {
      "state": "WV",
      "office": "State House",
      "district": "District 27",
      "candidate": "Craig Carpenter II",
      "party": "Other",
      "unopposed_in": "Primary",
      "source": "Ballotpedia"
    },
    {
      "state": "WV",
      "office": "State House",
      "district": "District 29",
      "candidate": "Wayne Williamson",
      "party": "Democrat",
      "unopposed_in": "Primary",
      "source": "Ballotpedia"
    },
    {
      "state": "WV",
      "office": "State House",
      "district": "District 30",
      "candidate": "Britney Brogan",
      "party": "Democrat",
      "unopposed_in": "Primary",
      "source": "Ballotpedia"
    },
    {
      "state": "WV",
      "office": "State House",
      "district": "District 32",
      "candidate": "April Estep",
      "party": "Democrat",
      "unopposed_in": "Primary",
      "source": "Ballotpedia"
    },
    {
      "state": "WV",
      "office": "State House",
      "district": "District 32",
      "candidate": "Josh Holstein",
      "party": "Republican",
      "unopposed_in": "Primary",
      "source": "Ballotpedia"
    },
    {
      "state": "WV",
      "office": "State House",
      "district": "District 33",
      "candidate": "George Howes",
      "party": "Democrat",
      "unopposed_in": "Primary",
      "source": "Ballotpedia"
    },
    {
      "state": "WV",
      "office": "State House",
      "district": "District 33",
      "candidate": "Jordan Bridges",
      "party": "Republican",
      "unopposed_in": "Primary",
      "source": "Ballotpedia"
    },
    {
      "state": "WV",
      "office": "State House",
      "district": "District 36",
      "candidate": "Tiffany Clemins",
      "party": "Democrat",
      "unopposed_in": "Primary",
      "source": "Ballotpedia"
    },
    {
      "state": "WV",
      "office": "State House",
      "district": "District 37",
      "candidate": "Polla McClellan Rumberg",
      "party": "Democrat",
      "unopposed_in": "Primary",
      "source": "Ballotpedia"
    },
    {
      "state": "WV",
      "office": "State House",
      "district": "District 37",
      "candidate": "Marty Gearheart",
      "party": "Republican",
      "unopposed_in": "Primary",
      "source": "Ballotpedia"
    },
    {
      "state": "WV",
      "office": "State House",
      "district": "District 38",
      "candidate": "Randa Faulkner",
      "party": "Democrat",
      "unopposed_in": "Primary",
      "source": "Ballotpedia"
    },
    {
      "state": "WV",
      "office": "State House",
      "district": "District 38",
      "candidate": "Joe Ellington",
      "party": "Republican",
      "unopposed_in": "Primary",
      "source": "Ballotpedia"
    },
    {
      "state": "WV",
      "office": "State House",
      "district": "District 39",
      "candidate": "Neal Vestal",
      "party": "Democrat",
      "unopposed_in": "Primary",
      "source": "Ballotpedia"
    },
    {
      "state": "WV",
      "office": "State House",
      "district": "District 39",
      "candidate": "Doug Smith",
      "party": "Republican",
      "unopposed_in": "Primary",
      "source": "Ballotpedia"
    },
    {
      "state": "WV",
      "office": "State House",
      "district": "District 40",
      "candidate": "Jim McNeely",
      "party": "Democrat",
      "unopposed_in": "Primary",
      "source": "Ballotpedia"
    },
    {
      "state": "WV",
      "office": "State House",
      "district": "District 41",
      "candidate": "Anna Ferraraccio",
      "party": "Democrat",
      "unopposed_in": "Primary",
      "source": "Ballotpedia"
    },
    {
      "state": "WV",
      "office": "State House",
      "district": "District 41",
      "candidate": "Jordan Maynor",
      "party": "Republican",
      "unopposed_in": "Primary",
      "source": "Ballotpedia"
    },
    {
      "state": "WV",
      "office": "State House",
      "district": "District 42",
      "candidate": "Addam Gibson",
      "party": "Democrat",
      "unopposed_in": "Primary",
      "source": "Ballotpedia"
    },
    {
      "state": "WV",
      "office": "State House",
      "district": "District 42",
      "candidate": "Brandon Steele",
      "party": "Republican",
      "unopposed_in": "Primary",
      "source": "Ballotpedia"
    },
    {
      "state": "WV",
      "office": "State House",
      "district": "District 44",
      "candidate": "Tony O. Martin",
      "party": "Democrat",
      "unopposed_in": "Primary",
      "source": "Ballotpedia"
    },
    {
      "state": "WV",
      "office": "State House",
      "district": "District 44",
      "candidate": "Carl Roop",
      "party": "Republican",
      "unopposed_in": "Primary",
      "source": "Ballotpedia"
    },
    {
      "state": "WV",
      "office": "State House",
      "district": "District 46",
      "candidate": "Paul Detch",
      "party": "Democrat",
      "unopposed_in": "Primary",
      "source": "Ballotpedia"
    },
    {
      "state": "WV",
      "office": "State House",
      "district": "District 48",
      "candidate": "Devin Spinks",
      "party": "Democrat",
      "unopposed_in": "Primary",
      "source": "Ballotpedia"
    },
    {
      "state": "WV",
      "office": "State House",
      "district": "District 48",
      "candidate": "Tom Clark",
      "party": "Republican",
      "unopposed_in": "Primary",
      "source": "Ballotpedia"
    },
    {
      "state": "WV",
      "office": "State House",
      "district": "District 49",
      "candidate": "Jean Nutter",
      "party": "Democrat",
      "unopposed_in": "Primary",
      "source": "Ballotpedia"
    },
    {
      "state": "WV",
      "office": "State House",
      "district": "District 50",
      "candidate": "Jerry Allen",
      "party": "Democrat",
      "unopposed_in": "Primary",
      "source": "Ballotpedia"
    },
    {
      "state": "WV",
      "office": "State House",
      "district": "District 50",
      "candidate": "David Pritt",
      "party": "Republican",
      "unopposed_in": "Primary",
      "source": "Ballotpedia"
    },
    {
      "state": "WV",
      "office": "State House",
      "district": "District 52",
      "candidate": "Thomas Jones",
      "party": "Democrat",
      "unopposed_in": "Primary",
      "source": "Ballotpedia"
    },
    {
      "state": "WV",
      "office": "State House",
      "district": "District 53",
      "candidate": "Chris Smith",
      "party": "Democrat",
      "unopposed_in": "Primary",
      "source": "Ballotpedia"
    },
    {
      "state": "WV",
      "office": "State House",
      "district": "District 54",
      "candidate": "Mike Pushkin",
      "party": "Democrat",
      "unopposed_in": "Primary",
      "source": "Ballotpedia"
    },
    {
      "state": "WV",
      "office": "State House",
      "district": "District 54",
      "candidate": "Julien Aklei",
      "party": "Republican",
      "unopposed_in": "Primary",
      "source": "Ballotpedia"
    },
    {
      "state": "WV",
      "office": "State House",
      "district": "District 55",
      "candidate": "Linda Bodie",
      "party": "Democrat",
      "unopposed_in": "Primary",
      "source": "Ballotpedia"
    },
    {
      "state": "WV",
      "office": "State House",
      "district": "District 55",
      "candidate": "JB Akers",
      "party": "Republican",
      "unopposed_in": "Primary",
      "source": "Ballotpedia"
    },
    {
      "state": "WV",
      "office": "State House",
      "district": "District 56",
      "candidate": "Kayla Young",
      "party": "Democrat",
      "unopposed_in": "Primary",
      "source": "Ballotpedia"
    },
    {
      "state": "WV",
      "office": "State House",
      "district": "District 57",
      "candidate": "Hollis Lewis",
      "party": "Democrat",
      "unopposed_in": "Primary",
      "source": "Ballotpedia"
    },
    {
      "state": "WV",
      "office": "State House",
      "district": "District 65",
      "candidate": "Matthew Kerner",
      "party": "Democrat",
      "unopposed_in": "Primary",
      "source": "Ballotpedia"
    },
    {
      "state": "WV",
      "office": "State House",
      "district": "District 65",
      "candidate": "Carl Martin",
      "party": "Republican",
      "unopposed_in": "Primary",
      "source": "Ballotpedia"
    },
    {
      "state": "WV",
      "office": "State House",
      "district": "District 66",
      "candidate": "Dama Nestor",
      "party": "Democrat",
      "unopposed_in": "Primary",
      "source": "Ballotpedia"
    },
    {
      "state": "WV",
      "office": "State House",
      "district": "District 66",
      "candidate": "Jonathan Kyle",
      "party": "Republican",
      "unopposed_in": "Primary",
      "source": "Ballotpedia"
    },
    {
      "state": "WV",
      "office": "State House",
      "district": "District 67",
      "candidate": "Cody Thompson",
      "party": "Democrat",
      "unopposed_in": "Primary",
      "source": "Ballotpedia"
    },
    {
      "state": "WV",
      "office": "State House",
      "district": "District 67",
      "candidate": "Elias Coop-Gonzalez",
      "party": "Republican",
      "unopposed_in": "Primary",
      "source": "Ballotpedia"
    },
    {
      "state": "WV",
      "office": "State House",
      "district": "District 70",
      "candidate": "Morgan Earp",
      "party": "Democrat",
      "unopposed_in": "Primary",
      "source": "Ballotpedia"
    },
    {
      "state": "WV",
      "office": "State House",
      "district": "District 70",
      "candidate": "Mickey Petitto",
      "party": "Republican",
      "unopposed_in": "Primary",
      "source": "Ballotpedia"
    },
    {
      "state": "WV",
      "office": "State House",
      "district": "District 74",
      "candidate": "Frankie Delapas",
      "party": "Democrat",
      "unopposed_in": "Primary",
      "source": "Ballotpedia"
    },
    {
      "state": "WV",
      "office": "State House",
      "district": "District 74",
      "candidate": "Mike DeVault",
      "party": "Republican",
      "unopposed_in": "Primary",
      "source": "Ballotpedia"
    },
    {
      "state": "WV",
      "office": "State House",
      "district": "District 75",
      "candidate": "Stephanie Spears Tomana",
      "party": "Democrat",
      "unopposed_in": "Primary",
      "source": "Ballotpedia"
    },
    {
      "state": "WV",
      "office": "State House",
      "district": "District 78",
      "candidate": "Diane Market Gaston",
      "party": "Democrat",
      "unopposed_in": "Primary",
      "source": "Ballotpedia"
    },
    {
      "state": "WV",
      "office": "State House",
      "district": "District 78",
      "candidate": "Eugene Chiarelli",
      "party": "Republican",
      "unopposed_in": "Primary",
      "source": "Ballotpedia"
    },
    {
      "state": "WV",
      "office": "State House",
      "district": "District 80",
      "candidate": "John Williams",
      "party": "Democrat",
      "unopposed_in": "Primary",
      "source": "Ballotpedia"
    },
    {
      "state": "WV",
      "office": "State House",
      "district": "District 80",
      "candidate": "Summer Hartley",
      "party": "Republican",
      "unopposed_in": "Primary",
      "source": "Ballotpedia"
    },
    {
      "state": "WV",
      "office": "State House",
      "district": "District 82",
      "candidate": "David McCormick",
      "party": "Republican",
      "unopposed_in": "Primary",
      "source": "Ballotpedia"
    },
    {
      "state": "WV",
      "office": "State House",
      "district": "District 88",
      "candidate": "Amanda Vincent",
      "party": "Democrat",
      "unopposed_in": "Primary",
      "source": "Ballotpedia"
    },
    {
      "state": "WV",
      "office": "State House",
      "district": "District 88",
      "candidate": "Rick Hillenbrand",
      "party": "Republican",
      "unopposed_in": "Primary",
      "source": "Ballotpedia"
    },
    {
      "state": "WV",
      "office": "State House",
      "district": "District 89",
      "candidate": "Alyson Reeves",
      "party": "Democrat",
      "unopposed_in": "Primary",
      "source": "Ballotpedia"
    },
    {
      "state": "WV",
      "office": "State House",
      "district": "District 89",
      "candidate": "Darren Thorne",
      "party": "Republican",
      "unopposed_in": "Primary",
      "source": "Ballotpedia"
    },
    {
      "state": "WV",
      "office": "State House",
      "district": "District 95",
      "candidate": "Debi Carroll",
      "party": "Democrat",
      "unopposed_in": "Primary",
      "source": "Ballotpedia"
    },
    {
      "state": "WV",
      "office": "State House",
      "district": "District 95",
      "candidate": "Charles Horst Sr.",
      "party": "Republican",
      "unopposed_in": "Primary",
      "source": "Ballotpedia"
    },
    {
      "state": "WV",
      "office": "State House",
      "district": "District 96",
      "candidate": "Aniqua Lower",
      "party": "Democrat",
      "unopposed_in": "Primary",
      "source": "Ballotpedia"
    },
    {
      "state": "WV",
      "office": "State House",
      "district": "District 97",
      "candidate": "Lucia Valentine",
      "party": "Democrat",
      "unopposed_in": "Primary",
      "source": "Ballotpedia"
    },
    {
      "state": "WV",
      "office": "State House",
      "district": "District 98",
      "candidate": "Troy Miller",
      "party": "Democrat",
      "unopposed_in": "Primary",
      "source": "Ballotpedia"
    },
    {
      "state": "WV",
      "office": "State House",
      "district": "District 99",
      "candidate": "Osmund Anderson",
      "party": "Democrat",
      "unopposed_in": "Primary",
      "source": "Ballotpedia"
    },
    {
      "state": "WV",
      "office": "State House",
      "district": "District 100",
      "candidate": "Maria Russo",
      "party": "Democrat",
      "unopposed_in": "Primary",
      "source": "Ballotpedia"
    },
    {
      "state": "WV",
      "office": "State House",
      "district": "District 100",
      "candidate": "William Ridenour",
      "party": "Republican",
      "unopposed_in": "Primary",
      "source": "Ballotpedia"
    }
  ]
}
